{
  "dist/hickory-root.es.js": {
    "bundled": 9076,
    "minified": 3573,
    "gzipped": 1486,
    "treeshaked": {
      "rollup": {
        "code": 32,
        "import_statements": 32
      },
      "webpack": {
        "code": 1828
      }
    }
  },
  "dist/hickory-root.js": {
    "bundled": 9203,
    "minified": 3684,
    "gzipped": 1522
  },
  "dist/hickory-root.umd.js": {
    "bundled": 11083,
    "minified": 3503,
    "gzipped": 1542
  },
  "dist/hickory-root.min.js": {
    "bundled": 11083,
    "minified": 3503,
    "gzipped": 1542
  }
}
