{
  "dist/hickory-location-utils.es.js": {
    "bundled": 873,
    "minified": 594,
    "gzipped": 249,
    "treeshaked": {
      "rollup": {
        "code": 0,
        "import_statements": 0
      },
      "webpack": {
        "code": 951
      }
    }
  },
  "dist/hickory-location-utils.js": {
    "bundled": 1099,
    "minified": 800,
    "gzipped": 316
  },
  "dist/hickory-location-utils.umd.js": {
    "bundled": 1460,
    "minified": 685,
    "gzipped": 378
  },
  "dist/hickory-location-utils.min.js": {
    "bundled": 1460,
    "minified": 685,
    "gzipped": 378
  }
}
